ts_sdk/__init__.py
ts_sdk/cli/__api.py
ts_sdk/cli/__deprecated.py
ts_sdk/cli/__init__.py
ts_sdk/cli/__init_cmd.py
ts_sdk/cli/__main__.py
ts_sdk/cli/__put_cmd.py
ts_sdk/cli/__utils.py
ts_sdk/cli/protocol-template/protocol/README.md.template
ts_sdk/cli/protocol-template/protocol/protocol.yml.template
ts_sdk/cli/protocol-template/protocol-v2/README.md.template
ts_sdk/cli/protocol-template/protocol-v2/protocol.json.template
ts_sdk/cli/protocol-template/protocol-v2/script.js.template
ts_sdk/cli/protocol-template/task-script/Pipfile
ts_sdk/cli/protocol-template/task-script/README.md.template
ts_sdk/cli/protocol-template/task-script/__test__/data/expected.json
ts_sdk/cli/protocol-template/task-script/__test__/data/input.json
ts_sdk/cli/protocol-template/task-script/__test__/test_business_logic.py
ts_sdk/cli/protocol-template/task-script/__test__/test_config.py
ts_sdk/cli/protocol-template/task-script/__test__/test_integration.py
ts_sdk/cli/protocol-template/task-script/config.json
ts_sdk/cli/protocol-template/task-script/main.py
ts_sdk/cli/put_cmd_helpers/__init__.py
ts_sdk/cli/put_cmd_helpers/upload_validator.py
ts_sdk/schemas/__init__.py
ts_sdk/schemas/config.schema.json
ts_sdk/schemas/protocol.schema.json
ts_sdk/schemas/protocol.v3.schema.json
ts_sdk/task/__exceptions.py
ts_sdk/task/__init__.py
ts_sdk/task/__task_script_runner.py
ts_sdk/task/__util_adapters/__init__.py
ts_sdk/task/__util_adapters/communication_format.py
ts_sdk/task/__util_adapters/curry_format.py
ts_sdk/task/__util_adapters/endpoint_adapter.py
ts_sdk/task/__util_adapters/make_adapter.py
ts_sdk/task/__util_artifact.py
ts_sdk/task/__util_command.py
ts_sdk/task/__util_config.py
ts_sdk/task/__util_datalake.py
ts_sdk/task/__util_decorators.py
ts_sdk/task/__util_es_datalake.py
ts_sdk/task/__util_fileinfo.py
ts_sdk/task/__util_log.py
ts_sdk/task/__util_merge.py
ts_sdk/task/__util_metadata.py
ts_sdk/task/__util_permalink.py
ts_sdk/task/__util_storage.py
ts_sdk/task/__util_task/__init__.py
ts_sdk-2.6.0.dist-info/METADATA
ts_sdk-2.6.0.dist-info/WHEEL
ts_sdk-2.6.0.dist-info/entry_points.txt
ts_sdk-2.6.0.dist-info/licenses/LICENSE.txt
ts_sdk-2.6.0.dist-info/RECORD
