Metadata-Version: 2.4
Name: ts-sdk
Version: 2.6.0
Summary: Tetrascience Python SDK
License: Apache-2.0
License-File: LICENSE.txt
Author: tetrascience
Requires-Python: >=3.9,<4
Classifier: License :: OSI Approved :: Apache Software License
Classifier: Programming Language :: Python :: 3
Classifier: Programming Language :: Python :: 3.9
Classifier: Programming Language :: Python :: 3.10
Classifier: Programming Language :: Python :: 3.11
Classifier: Programming Language :: Python :: 3.12
Classifier: Programming Language :: Python :: 3.13
Classifier: Programming Language :: Python :: 3.14
Provides-Extra: testing
Requires-Dist: boto3 (>=1.16.3,<2.0.0)
Requires-Dist: colorama (>=0.4.4,<0.5.0)
Requires-Dist: loguru (>=0.7.3,<0.8.0)
Requires-Dist: pytest (>=8.3.4,<9.0.0) ; (python_version >= "3.10") and (extra == "testing")
Requires-Dist: pyyaml (>=6.0.1,<7.0.0) ; (python_version >= "3.10") and (extra == "testing")
Requires-Dist: requests (>=2.22.0,<3.0.0)
Requires-Dist: simplejson (>=3.17.6,<4.0.0)
Requires-Dist: smart-open[s3] (>=7,<8)
Requires-Dist: tenacity (>=8.5.0,<9.0.0)
Requires-Dist: ts-ids-validator (>=1.1.0,<2.0.0)
Requires-Dist: typing-extensions (>=4,<5)
Project-URL: Homepage, https://developers.tetrascience.com
